cdc_py/__init__.py
cdc_py-0.0.1.dist-info/WHEEL
cdc_py-0.0.1.dist-info/entry_points.txt
cdc_py-0.0.1.dist-info/METADATA
cdc_py-0.0.1.dist-info/RECORD
