Metadata-Version: 2.3
Name: cdc-py
Version: 0.0.1
Summary: CDC
Author: Dmitry Drozdov
Author-email: Dmitry Drozdov <ds.drozdov@gmail.com>
Requires-Python: >=3.13
